base_url/__init__.py
base_url/__version__.py
base_url/encode_url.py
tests/__init__.py
base_url-0.0.1.dist-info/LICENSE
base_url-0.0.1.dist-info/METADATA
base_url-0.0.1.dist-info/WHEEL
base_url-0.0.1.dist-info/top_level.txt
base_url-0.0.1.dist-info/RECORD
