Metadata-Version: 2.1
Name: base-url
Version: 0.0.1
Summary: Useful tools to work with Base64 url Encode / Decode in Python
Home-page: https://github.com/willyfaq/base_url
Author: Willyfaq
Author-email: willyfaqurokhim@gmail.com
License: UNKNOWN
Project-URL: Bug Tracker, https://github.com/willyfaq/base_url/issues
Platform: UNKNOWN
Classifier: Programming Language :: Python :: 3
Classifier: License :: OSI Approved :: MIT License
Classifier: Operating System :: OS Independent
Requires-Python: >=3.6
